aws_cdk_constructs_config_provider/__init__.py
aws_cdk_constructs_config_provider/config_provider.py
aws_cdk_constructs_config_provider/default_settings.py
aws_cdk_constructs_config_provider/environment_parameters.py
aws_cdk_constructs_config_provider/tags.py
aws_cdk_constructs_config_provider/tags_mandatory.py
aws_cdk_constructs_config_provider/tags_scheduler.py
aws_cdk_constructs_config_provider-0.1.0.dist-info/METADATA
aws_cdk_constructs_config_provider-0.1.0.dist-info/WHEEL
aws_cdk_constructs_config_provider-0.1.0.dist-info/RECORD
