Metadata-Version: 2.1
Name: aws-cdk-constructs-config-provider
Version: 0.1.0
Summary: 
Author: Sergio
Author-email: sergio.penafilgueira@fao.org
Requires-Python: >=3.9.19,<4.0.0
Classifier: Programming Language :: Python :: 3
Classifier: Programming Language :: Python :: 3.10
Classifier: Programming Language :: Python :: 3.11
Classifier: Programming Language :: Python :: 3.12
Requires-Dist: aws-cdk-lib (>=2.123.0,<3.0.0)
Requires-Dist: pydantic-settings (>=2.0.2,<3.0.0)
Requires-Dist: python-dotenv (>=0.21.0,<0.22.0)
